plone.portlets-3.0.3-py3.13-nspkg.pth
plone/portlets/CREDITS.txt
plone/portlets/README.txt
plone/portlets/TODO.txt
plone/portlets/__init__.py
plone/portlets/assignable.py
plone/portlets/configure.zcml
plone/portlets/constants.py
plone/portlets/events.py
plone/portlets/interfaces.py
plone/portlets/manager.py
plone/portlets/registration.py
plone/portlets/retriever.py
plone/portlets/settings.py
plone/portlets/storage.py
plone/portlets/tests.py
plone/portlets/uisupport.txt
plone/portlets/utils.py
plone/portlets/utils.txt
plone_portlets-3.0.3.dist-info/METADATA
plone_portlets-3.0.3.dist-info/WHEEL
plone_portlets-3.0.3.dist-info/namespace_packages.txt
plone_portlets-3.0.3.dist-info/top_level.txt
plone_portlets-3.0.3.dist-info/RECORD
