Metadata-Version: 2.4
Name: plone.portlets
Version: 3.0.3
Summary: An extension of zope.viewlet to support dynamic portlets
Home-page: https://github.com/plone/plone.portlets
Author: Plone Foundation
Author-email: plone-developers@lists.sourceforge.net
License: GPL version 2
Keywords: portlet viewlet
Classifier: Development Status :: 5 - Production/Stable
Classifier: Environment :: Web Environment
Classifier: Framework :: Plone
Classifier: Framework :: Plone :: 6.0
Classifier: Framework :: Plone :: Core
Classifier: Framework :: Zope :: 5
Classifier: License :: OSI Approved :: GNU General Public License v2 (GPLv2)
Classifier: Operating System :: OS Independent
Classifier: Programming Language :: Python
Classifier: Programming Language :: Python :: 3.8
Classifier: Programming Language :: Python :: 3.9
Classifier: Programming Language :: Python :: 3.10
Classifier: Programming Language :: Python :: 3.11
Requires-Python: >=3.8
Requires-Dist: BTrees
Requires-Dist: setuptools
Requires-Dist: ZODB
Requires-Dist: plone.memoize
Requires-Dist: persistent
Requires-Dist: zope.annotation
Requires-Dist: zope.component
Requires-Dist: zope.container
Requires-Dist: zope.contentprovider
Requires-Dist: zope.interface
Requires-Dist: zope.location
Requires-Dist: zope.publisher
Requires-Dist: zope.schema
Provides-Extra: test
Requires-Dist: zope.browserpage; extra == "test"
Requires-Dist: zope.configuration; extra == "test"
Requires-Dist: zope.location; extra == "test"
Requires-Dist: zope.security; extra == "test"
Requires-Dist: zope.site; extra == "test"
Requires-Dist: zope.testing; extra == "test"
Dynamic: author
Dynamic: author-email
Dynamic: classifier
Dynamic: description
Dynamic: description-content-type
Dynamic: home-page
Dynamic: keywords
Dynamic: license
Dynamic: provides-extra
Dynamic: requires-dist
Dynamic: requires-python
Dynamic: summary
